huaweicloudsdkucs/__init__.py
huaweicloudsdkucs/v1/__init__.py
huaweicloudsdkucs/v1/ucs_async_client.py
huaweicloudsdkucs/v1/ucs_client.py
huaweicloudsdkucs/v1/model/__init__.py
huaweicloudsdkucs/v1/model/addon_instance.py
huaweicloudsdkucs/v1/model/addon_instance_spec.py
huaweicloudsdkucs/v1/model/addon_instance_status.py
huaweicloudsdkucs/v1/model/addon_object_meta.py
huaweicloudsdkucs/v1/model/addon_template.py
huaweicloudsdkucs/v1/model/addon_template_spec.py
huaweicloudsdkucs/v1/model/addon_version.py
huaweicloudsdkucs/v1/model/api_enablement.py
huaweicloudsdkucs/v1/model/api_resource.py
huaweicloudsdkucs/v1/model/artifact.py
huaweicloudsdkucs/v1/model/auth_info.py
huaweicloudsdkucs/v1/model/cluster.py
huaweicloudsdkucs/v1/model/cluster_affinity.py
huaweicloudsdkucs/v1/model/cluster_cert.py
huaweicloudsdkucs/v1/model/cluster_group.py
huaweicloudsdkucs/v1/model/cluster_group_condition.py
huaweicloudsdkucs/v1/model/cluster_group_spec.py
huaweicloudsdkucs/v1/model/cluster_group_status.py
huaweicloudsdkucs/v1/model/cluster_info.py
huaweicloudsdkucs/v1/model/cluster_join_group_request_body.py
huaweicloudsdkucs/v1/model/cluster_reconcile_status.py
huaweicloudsdkucs/v1/model/cluster_spec.py
huaweicloudsdkucs/v1/model/cluster_status.py
huaweicloudsdkucs/v1/model/common_quotas.py
huaweicloudsdkucs/v1/model/condition_status.py
huaweicloudsdkucs/v1/model/config_set_response.py
huaweicloudsdkucs/v1/model/connect_endpoint.py
huaweicloudsdkucs/v1/model/constraint.py
huaweicloudsdkucs/v1/model/constraint_spec.py
huaweicloudsdkucs/v1/model/container_status.py
huaweicloudsdkucs/v1/model/content.py
huaweicloudsdkucs/v1/model/context.py
huaweicloudsdkucs/v1/model/create_addon_instance_request.py
huaweicloudsdkucs/v1/model/create_addon_instance_response.py
huaweicloudsdkucs/v1/model/create_cluster_conf_request.py
huaweicloudsdkucs/v1/model/create_cluster_conf_response.py
huaweicloudsdkucs/v1/model/create_cluster_group_policy_instance_request.py
huaweicloudsdkucs-3.1.184.dist-info/METADATA
huaweicloudsdkucs-3.1.184.dist-info/WHEEL
huaweicloudsdkucs-3.1.184.dist-info/licenses/LICENSE
huaweicloudsdkucs-3.1.184.dist-info/RECORD
